topsis_nishant_76.py
topsis_nishant_76-12.1.6.data/scripts/topsis_cli
topsis_nishant_76-12.1.6.dist-info/LICENSE
topsis_nishant_76-12.1.6.dist-info/METADATA
topsis_nishant_76-12.1.6.dist-info/WHEEL
topsis_nishant_76-12.1.6.dist-info/top_level.txt
topsis_nishant_76-12.1.6.dist-info/RECORD
