Metadata-Version: 2.1
Name: topsis-nishant-76
Version: 12.1.6
Summary: A topsis Implementation in python for multi-criteria decision making
Home-page: https://github.com/nishu195/nishant_outlier_76
Author: Nishant Goel
Author-email: ngoel_be17@thapar.edu
License: UNKNOWN
Keywords: command-line,Outliers,outlier-removal,row-removal
Platform: UNKNOWN
Classifier: Programming Language :: Python :: 3
Classifier: License :: OSI Approved :: MIT License
Classifier: Operating System :: OS Independent
Requires-Python: >=3.6
Requires-Dist: numpy
Requires-Dist: pandas
Requires-Dist: scipy
